mech/__init__.py
mech/mech.py
mech/mech_box.py
mech/mech_cli.py
mech/mech_cloud.py
mech/mech_cloud_instance.py
mech/mech_instance.py
mech/mech_snapshot.py
mech/mech_winrm.py
mech/utils.py
mech/vbm.py
mech/vmrun.py
mikemech-0.9.3.dist-info/LICENSE
mikemech-0.9.3.dist-info/METADATA
mikemech-0.9.3.dist-info/WHEEL
mikemech-0.9.3.dist-info/entry_points.txt
mikemech-0.9.3.dist-info/top_level.txt
mikemech-0.9.3.dist-info/RECORD
