Metadata-Version: 2.1
Name: mikemech
Version: 0.9.3
Summary: Tool for command line virtual machines
Home-page: https://github.com/mkinney/mech
Author: Kevin Chung, Germán Méndez Bravo, Mike Kinney
Author-email: kchung@nyu.edu, german.mb@gmail.com, mike.kinney@gmail.com
License: MIT
Download-URL: https://github.com/mkinney/mech/tarball/master
Keywords: vagrant,vmware,vmrun,tool,virtualization
Platform: UNKNOWN
Classifier: Development Status :: 4 - Beta
Classifier: Intended Audience :: Developers
Classifier: Intended Audience :: Information Technology
Classifier: Intended Audience :: End Users/Desktop
Classifier: Intended Audience :: Science/Research
Classifier: Intended Audience :: System Administrators
Classifier: License :: OSI Approved :: MIT License
Classifier: Operating System :: OS Independent
Classifier: Topic :: System :: Emulators
Classifier: Topic :: Utilities
Classifier: Programming Language :: Python :: 3.7
Classifier: Programming Language :: Python :: 3.8
Requires-Python: >=3.7
Requires-Dist: requests
Requires-Dist: click
Requires-Dist: colorama
Requires-Dist: pyinfra
Requires-Dist: pypsrp
